s00zzang_lotto/__init__.py
s00zzang_lotto/s00zzang_lotto.py
s00zzang_lotto-0.2.4.dist-info/METADATA
s00zzang_lotto-0.2.4.dist-info/WHEEL
s00zzang_lotto-0.2.4.dist-info/entry_points.txt
s00zzang_lotto-0.2.4.dist-info/top_level.txt
s00zzang_lotto-0.2.4.dist-info/RECORD
