Metadata-Version: 2.1
Name: s00zzang_lotto
Version: 0.2.4
Summary: Default template for PDM package
Author-email: S00zzang <sujinpark8719561@gmail.com>
License: MIT
Requires-Python: >=3.9
